heallol/__init__.py
heallol/tiktok.py
heallol-0.1.0.dist-info/LICENSE
heallol-0.1.0.dist-info/METADATA
heallol-0.1.0.dist-info/WHEEL
heallol-0.1.0.dist-info/top_level.txt
heallol-0.1.0.dist-info/RECORD
