Metadata-Version: 2.1
Name: heallol
Version: 0.1.0
Summary: API wrapper for the Heal API.
Home-page: https://github.com/heal-devs/heal-py
Author: aiokev
License: GPL-3.0
Keywords: python,heal,api,wrapper,healpy,heal.lol
Classifier: Intended Audience :: Developers
Classifier: Operating System :: OS Independent
Requires-Python: >=3.9
License-File: LICENSE
